whatthetype/whatthetype.py
whatthetype-1.1.dist-info/METADATA
whatthetype-1.1.dist-info/WHEEL
whatthetype-1.1.dist-info/top_level.txt
whatthetype-1.1.dist-info/RECORD
