Metadata-Version: 2.2
Name: whatthetype
Version: 1.1
Summary: Derives type hints from data captured during runtime. Updates source files with type hints. USE SOURCE CONTROL before upating in-place!!!!
Author: Witold Zolnowski
Requires-Dist: autopep8>=2.0.0
Dynamic: author
Dynamic: description
Dynamic: description-content-type
Dynamic: requires-dist
Dynamic: summary
